fastapiez/__init__.py
fastapiez/code/__init__.py
fastapiez/code/alembic/alembic.py
fastapiez/code/code_objects/__init__.py
fastapiez/code/code_objects/base.py
fastapiez/code/code_objects/database.py
fastapiez/code/code_objects/dependacies.py
fastapiez/code/code_objects/main.py
fastapiez/code/code_objects/model.py
fastapiez/code/code_objects/repository.py
fastapiez/code/code_objects/routes.py
fastapiez/code/code_objects/schema.py
fastapiez/code/code_objects/service.py
fastapiez/code/code_objects/settings.py
fastapiez/code/code_objects/tests.py
fastapiez/code/config.py
fastapiez/code/User/authentication.py
fastapiez/code/utils.py
fastapiez/create_project.py
fastapiez/errors.py
fastapiez/exceptions.py
fastapiez/main.py
fastapiez/py.typed
fastapiez/relationships.py
fastapiez/sqlalch_types.py
fastapiez/types.py
fastapiez/validators.py
fastapiez-0.0.1006.dist-info/LICENSE
fastapiez-0.0.1006.dist-info/METADATA
fastapiez-0.0.1006.dist-info/WHEEL
fastapiez-0.0.1006.dist-info/RECORD
