Metadata-Version: 2.1
Name: fastapiez
Version: 0.0.1006
Summary: Create fastapi ez
License: MIT
Author: frenki123
Author-email: marko.frankola@gmail.com
Requires-Python: >=3.11,<4.0
Classifier: License :: OSI Approved :: MIT License
Classifier: Programming Language :: Python :: 3
Classifier: Programming Language :: Python :: 3.11
Requires-Dist: SQLAlchemy (>=2.0.0,<3.0.0)
Requires-Dist: ordered-set (>=4.0.0,<5.0.0)
Requires-Dist: pydantic (>=2.1.0,<3.0.0)
